invariant_client/VERSION
invariant_client/__init__.py
invariant_client/__main__.py
invariant_client/auth/__init__.py
invariant_client/auth/auth.py
invariant_client/aws_pruner/__init__.py
invariant_client/aws_pruner/aws_pruner.py
invariant_client/aws_pruner/aws_pruner_integration.py
invariant_client/aws_pruner.py
invariant_client/aws_pruner_integration.py
invariant_client/base_command/__init__.py
invariant_client/base_command/base_command.py
invariant_client/bindings/invariant_instance_client/__init__.py
invariant_client/bindings/invariant_instance_client/api/__init__.py
invariant_client/bindings/invariant_instance_client/api/organization/__init__.py
invariant_client/bindings/invariant_instance_client/api/organization/attach_resource_set_organization_name_api_v_1_networks_network_uuid_attach_resource_set_post.py
invariant_client/bindings/invariant_instance_client/api/organization/autocomplete_channels_organization_name_api_v1_channels_autocomplete_get.py
invariant_client/bindings/invariant_instance_client/api/organization/create_editable_document_organization_name_api_v_1_edoc_post.py
invariant_client/bindings/invariant_instance_client/api/organization/create_integration_organization_name_api_v_1_integrations_post.py
invariant_client/bindings/invariant_instance_client/api/organization/create_monitor_targets_organization_name_api_v_1_monitor_targets_post.py
invariant_client/bindings/invariant_instance_client/api/organization/create_network_organization_name_api_v_1_networks_post.py
invariant_client/bindings/invariant_instance_client/api/organization/create_notification_group_organization_name_api_v_1_notification_groups_post.py
invariant_client/bindings/invariant_instance_client/api/organization/create_resource_set_organization_name_api_v_1_resource_sets_post.py
invariant_client/bindings/invariant_instance_client/api/organization/create_security_integration_organization_name_api_v_1_security_integrations_post.py
invariant_client-2.1.0.dist-info/LICENSE
invariant_client-2.1.0.dist-info/METADATA
invariant_client-2.1.0.dist-info/WHEEL
invariant_client-2.1.0.dist-info/entry_points.txt
invariant_client-2.1.0.dist-info/RECORD
