Metadata-Version: 2.3
Name: invariant-client
Version: 2.1.0
Summary: Invariant: manage ACLs in an entirely new way
Author: Rob Ankeny
Author-email: ankenyr@gmail.com
Requires-Python: >=3.10,<4.0
Classifier: Programming Language :: Python :: 3
Classifier: Programming Language :: Python :: 3.10
Classifier: Programming Language :: Python :: 3.11
Classifier: Programming Language :: Python :: 3.12
Classifier: Programming Language :: Python :: 3.13
Requires-Dist: attrs (>=21.3.0)
Requires-Dist: backoff (>=2.2.1,<3.0.0)
Requires-Dist: boto3 (>=1.36.12,<2.0.0)
Requires-Dist: boto3-stubs[ec2,elbv2,rds] (>=1.36.15,<2.0.0)
Requires-Dist: httpx (>=0.20.0,<0.26.0)
Requires-Dist: ijson (>=3.3.0,<4.0.0)
Requires-Dist: keyring (>=25.6.0,<26.0.0)
Requires-Dist: msal-extensions (>=1.3.1,<2.0.0)
Requires-Dist: netconan (>=0.13.0,<0.14.0)
Requires-Dist: netmiko (>=4.5.0,<5.0.0)
Requires-Dist: numpy (>=1.26,<2)
Requires-Dist: pandas (>=2.2.0,<3.0.0)
Requires-Dist: pyarrow (>=13,<15)
Requires-Dist: pydantic (>=2.4.2,<3.0.0)
Requires-Dist: python-dateutil (>=2.8.0,<3.0.0)
Requires-Dist: pyyaml (>=6.0.2,<7.0.0)
Requires-Dist: rich (>=13.7.0,<14.0.0)
Requires-Dist: tabulate (>=0.9.0,<0.10.0)
Requires-Dist: xdg-base-dirs (>=6.0.2,<7.0.0)
